coding_agent/__init__.py
coding_agent/action_executor.py
coding_agent/agent.py
coding_agent/ai_ml_template.py
coding_agent/cli.py
coding_agent/code_analyzer.py
coding_agent/config.py
coding_agent/context_cli.py
coding_agent/context_manager.py
coding_agent/conversation_manager.py
coding_agent/custom_model_manager.py
coding_agent/dashboard.py
coding_agent/django_template.py
coding_agent/error_handler.py
coding_agent/fastapi_template.py
coding_agent/file_ops.py
coding_agent/flask_template.py
coding_agent/git_ops.py
coding_agent/history_manager.py
coding_agent/language_detector.py
coding_agent/logger.py
coding_agent/mcp_manager.py
coding_agent/model_manager.py
coding_agent/nodejs_template.py
coding_agent/performance.py
coding_agent/plugin_manager.py
coding_agent/project_templates.py
coding_agent/react_template.py
coding_agent/security_cli.py
coding_agent/security_manager.py
coding_agent/visualization_manager.py
coding_agent/history/conversation_20251112_113043_748718.txt
coding_agent/provider/base.py
coding_agent/provider/custom.py
coding_agent/provider/google.py
coding_agent/provider/groq.py
coding_agent/provider/mcp.py
coding_agent/provider/multiprovider.py
codeius-1.0.2.dist-info/METADATA
codeius-1.0.2.dist-info/WHEEL
codeius-1.0.2.dist-info/entry_points.txt
codeius-1.0.2.dist-info/licenses/LICENSE
codeius-1.0.2.dist-info/RECORD
