Metadata-Version: 2.4
Name: codeius
Version: 1.0.2
Summary: AI-powered coding assistant with multiple tools and visual interface
Author-email: MuhammadUsmanGM <MuhammadUsmanGM@users.noreply.github.com>
License: MIT
License-File: LICENSE
Classifier: Development Status :: 4 - Beta
Classifier: Intended Audience :: Developers
Classifier: License :: OSI Approved :: MIT License
Classifier: Programming Language :: Python :: 3.11
Classifier: Programming Language :: Python :: 3.12
Classifier: Programming Language :: Python :: 3.13
Classifier: Topic :: Software Development :: Build Tools
Requires-Python: >=3.11
Requires-Dist: build>=1.3.0
Requires-Dist: flake8>=7.3.0
Requires-Dist: flask>=3.1.2
Requires-Dist: gitpython>=3.1.45
Requires-Dist: matplotlib>=3.8.0
Requires-Dist: networkx>=3.2.1
Requires-Dist: pillow>=12.0.0
Requires-Dist: prompt-toolkit>=3.0.52
Requires-Dist: pydantic>=2.12.4
Requires-Dist: pyfiglet>=1.0.0
Requires-Dist: pytesseract>=0.3.13
Requires-Dist: pytest>=9.0.0
Requires-Dist: python-dotenv>=1.2.1
Requires-Dist: pyyaml>=6.0
Requires-Dist: radon>=6.0.1
Requires-Dist: requests>=2.32.5
Requires-Dist: rich>=14.2.0
